odoo8_addon_partner_capital-8.0.1.0.0.99.dev18-py3.8-nspkg.pth
odoo_addons/partner_capital/README.rst
odoo_addons/partner_capital/__init__.py
odoo_addons/partner_capital/__openerp__.py
odoo_addons/partner_capital/i18n/de.po
odoo_addons/partner_capital/i18n/es.po
odoo_addons/partner_capital/i18n/eu.po
odoo_addons/partner_capital/i18n/fi.po
odoo_addons/partner_capital/i18n/it.po
odoo_addons/partner_capital/i18n/partner_capital.pot
odoo_addons/partner_capital/i18n/sl.po
odoo_addons/partner_capital/models/__init__.py
odoo_addons/partner_capital/models/res_partner.py
odoo_addons/partner_capital/models/res_partner_turnover_range.py
odoo_addons/partner_capital/security/ir.model.access.csv
odoo_addons/partner_capital/static/description/icon.png
odoo_addons/partner_capital/views/res_partner_turnover_range_view.xml
odoo_addons/partner_capital/views/res_partner_view.xml
odoo8_addon_partner_capital-8.0.1.0.0.99.dev18.dist-info/METADATA
odoo8_addon_partner_capital-8.0.1.0.0.99.dev18.dist-info/WHEEL
odoo8_addon_partner_capital-8.0.1.0.0.99.dev18.dist-info/namespace_packages.txt
odoo8_addon_partner_capital-8.0.1.0.0.99.dev18.dist-info/top_level.txt
odoo8_addon_partner_capital-8.0.1.0.0.99.dev18.dist-info/RECORD
